{ "command": "room", "venue": "Pavillion", "room": "Balcony", "size": "large" }
{ "command": "room", "venue": "Hotel", "room": "Bar", "size": "medium" }
{ "command": "room", "venue": "Hotel", "room": "Rooftop", "size": "medium" }
{ "command": "request", "id": "AGM", "start": "2020-01-10", "end": "2020-01-11", "small": 0, "medium": 0, "large": 1 }
{ "command": "list", "venue": "Hotel" }
{ "command": "change", "id": "AGM", "start": "2020-05-02", "end": "2020-05-03", "small": 0, "medium": 2, "large": 0 }
{ "command": "request", "id": "AA meeting", "start": "2020-05-01", "end": "2020-05-03", "small": 0, "medium": 2, "large": 0 }
{ "command": "list", "venue": "Hotel" }
{ "command": "list", "venue": "Pavillion" }